<?xml version="1.0" encoding="UTF-8" standalone="no"?><rdf:RDF xmlns:rdf="http://www.w3.org/1999/02/22-rdf-syntax-ns#" xmlns:daml="http://www.daml.org/2001/03/daml+oil" xmlns:expr="http://www.daml.org/services/owl-s/1.2/generic/Expression.owl#" xmlns:owl="http://www.w3.org/2002/07/owl#" xmlns:process="http://www.daml.org/services/owl-s/1.2/Process.owl#" xmlns:rdfs="http://www.w3.org/2000/01/rdf-schema#" xmlns:service="http://www.daml.org/services/owl-s/1.2/Service.owl#" xmlns:swrl="http://www.w3.org/2003/11/swrl#" xml:base="http://magus.online/evaluation/service/service/ServiceC65S7ServiceC59S11"><service:Service rdf:ID="ServiceC65S7ServiceC59S11"><service:describedBy><process:AtomicProcess rdf:ID="ServiceC65S7ServiceC59S11Process"><service:describes rdf:resource="#ServiceC65S7ServiceC59S11"/><process:hasInput><process:Input rdf:ID="inpc7b3db5d71"><process:parameterType rdf:datatype="http://www.w3.org/2001/XMLSchema#anyURI">http://ls3.rnet.ryerson.ca/people/mahdi/magus/owl/eval.owl#c7b3db5d7</process:parameterType></process:Input></process:hasInput><process:hasInput><process:Input rdf:ID="inpce9ede17f1"><process:parameterType rdf:datatype="http://www.w3.org/2001/XMLSchema#anyURI">http://ls3.rnet.ryerson.ca/people/mahdi/magus/owl/eval.owl#ce9ede17f</process:parameterType></process:Input></process:hasInput><process:hasInput><process:Input rdf:ID="inpc0fc867ab1"><process:parameterType rdf:datatype="http://www.w3.org/2001/XMLSchema#anyURI">http://ls3.rnet.ryerson.ca/people/mahdi/magus/owl/eval.owl#c0fc867ab</process:parameterType></process:Input></process:hasInput><process:hasInput><process:Input rdf:ID="inpc1c5959b01"><process:parameterType rdf:datatype="http://www.w3.org/2001/XMLSchema#anyURI">http://ls3.rnet.ryerson.ca/people/mahdi/magus/owl/eval.owl#c1c5959b0</process:parameterType></process:Input></process:hasInput><process:hasInput><process:Input rdf:ID="inpc9813ee281"><process:parameterType rdf:datatype="http://www.w3.org/2001/XMLSchema#anyURI">http://ls3.rnet.ryerson.ca/people/mahdi/magus/owl/eval.owl#c9813ee28</process:parameterType></process:Input></process:hasInput><process:hasOutput><process:Output rdf:ID="outcdd525e111"><process:parameterType rdf:datatype="http://www.w3.org/2001/XMLSchema#anyURI">http://ls3.rnet.ryerson.ca/people/mahdi/magus/owl/eval.owl#cdd525e11</process:parameterType></process:Output></process:hasOutput><process:hasOutput><process:Output rdf:ID="outc04d7f5631"><process:parameterType rdf:datatype="http://www.w3.org/2001/XMLSchema#anyURI">http://ls3.rnet.ryerson.ca/people/mahdi/magus/owl/eval.owl#c04d7f563</process:parameterType></process:Output></process:hasOutput><process:hasOutput><process:Output rdf:ID="outc7b3db5d71"><process:parameterType rdf:datatype="http://www.w3.org/2001/XMLSchema#anyURI">http://ls3.rnet.ryerson.ca/people/mahdi/magus/owl/eval.owl#c7b3db5d7</process:parameterType></process:Output></process:hasOutput><process:hasOutput><process:Output rdf:ID="outc532654e41"><process:parameterType rdf:datatype="http://www.w3.org/2001/XMLSchema#anyURI">http://ls3.rnet.ryerson.ca/people/mahdi/magus/owl/eval.owl#c532654e4</process:parameterType></process:Output></process:hasOutput><process:hasOutput><process:Output rdf:ID="outc9c7728531"><process:parameterType rdf:datatype="http://www.w3.org/2001/XMLSchema#anyURI">http://ls3.rnet.ryerson.ca/people/mahdi/magus/owl/eval.owl#c9c772853</process:parameterType></process:Output></process:hasOutput><process:hasOutput><process:Output rdf:ID="outc36aa275a1"><process:parameterType rdf:datatype="http://www.w3.org/2001/XMLSchema#anyURI">http://ls3.rnet.ryerson.ca/people/mahdi/magus/owl/eval.owl#c36aa275a</process:parameterType></process:Output></process:hasOutput><process:hasOutput><process:Output rdf:ID="outc6085cf851"><process:parameterType rdf:datatype="http://www.w3.org/2001/XMLSchema#anyURI">http://ls3.rnet.ryerson.ca/people/mahdi/magus/owl/eval.owl#c6085cf85</process:parameterType></process:Output></process:hasOutput><process:hasPrecondition><expr:SWRL-Condition rdf:ID="ServiceC65S7ServiceC59S11Prec"><expr:expressionObject><swrl:AtomList><rdf:first><swrl:ClassAtom><swrl:classPredicate rdf:resource="http://ls3.rnet.ryerson.ca/people/mahdi/magus/owl/eval.owl#c7b3db5d7"/><swrl:argument1 rdf:resource="http://magus.online/evaluation/service/service/ServiceC65S7ServiceC59S11#inpc7b3db5d71"/></swrl:ClassAtom></rdf:first><rdf:rest><swrl:AtomList><rdf:first><swrl:ClassAtom><swrl:classPredicate rdf:resource="http://ls3.rnet.ryerson.ca/people/mahdi/magus/owl/eval.owl#ce9ede17f"/><swrl:argument1 rdf:resource="http://magus.online/evaluation/service/service/ServiceC65S7ServiceC59S11#inpce9ede17f1"/></swrl:ClassAtom></rdf:first><rdf:rest><swrl:AtomList><rdf:first><swrl:ClassAtom><swrl:classPredicate rdf:resource="http://ls3.rnet.ryerson.ca/people/mahdi/magus/owl/eval.owl#c0fc867ab"/><swrl:argument1 rdf:resource="http://magus.online/evaluation/service/service/ServiceC65S7ServiceC59S11#inpc0fc867ab1"/></swrl:ClassAtom></rdf:first><rdf:rest><swrl:AtomList><rdf:first><swrl:ClassAtom><swrl:classPredicate rdf:resource="http://ls3.rnet.ryerson.ca/people/mahdi/magus/owl/eval.owl#c1c5959b0"/><swrl:argument1 rdf:resource="http://magus.online/evaluation/service/service/ServiceC65S7ServiceC59S11#inpc1c5959b01"/></swrl:ClassAtom></rdf:first><rdf:rest><swrl:AtomList><rdf:first><swrl:ClassAtom><swrl:classPredicate rdf:resource="http://ls3.rnet.ryerson.ca/people/mahdi/magus/owl/eval.owl#c9813ee28"/><swrl:argument1 rdf:resource="http://magus.online/evaluation/service/service/ServiceC65S7ServiceC59S11#inpc9813ee281"/></swrl:ClassAtom></rdf:first><rdf:rest rdf:resource="http://www.w3.org/1999/02/22-rdf-syntax-ns#nil"/></swrl:AtomList></rdf:rest></swrl:AtomList></rdf:rest></swrl:AtomList></rdf:rest></swrl:AtomList></rdf:rest></swrl:AtomList></expr:expressionObject><expr:expressionLanguage rdf:resource="http://www.daml.org/services/owl-s/1.2/generic/Expression.owl#SWRL"/></expr:SWRL-Condition></process:hasPrecondition><process:hasResult><expr:SWRL-Condition rdf:ID="ServiceC65S7ServiceC59S11Eff"><expr:expressionObject><swrl:AtomList><rdf:first><swrl:IndividualPropertyAtom><swrl:propertyPredicate rdf:resource="http://ls3.rnet.ryerson.ca/people/mahdi/magus/owl/eval.owl#pea163e0f"/><swrl:argument1 rdf:resource="http://magus.online/evaluation/service/service/ServiceC65S7ServiceC59S11#outc7b3db5d71"/><swrl:argument2 rdf:resource="http://magus.online/evaluation/service/service/ServiceC65S7ServiceC59S11#outc532654e41"/></swrl:IndividualPropertyAtom></rdf:first><rdf:rest rdf:resource="http://www.w3.org/1999/02/22-rdf-syntax-ns#nil"/></swrl:AtomList></expr:expressionObject><expr:expressionLanguage rdf:resource="http://www.daml.org/services/owl-s/1.2/generic/Expression.owl#SWRL"/></expr:SWRL-Condition></process:hasResult></process:AtomicProcess></service:describedBy></service:Service></rdf:RDF>