<?xml version="1.0" encoding="UTF-8" standalone="no"?><configuration xmlns:xsi="http://www.w3.org/2001/XMLSchema-instance" xsi:noNamespaceSchemaLocation="http://magus.online/resources/schema/servicemashupconfiguration.xsd"><ontologies><ontology address="contextModel.xml"/></ontologies><featuremodel address="fm.xml"/><services><service address="services/ServiceC363S6.xml"/><service address="services/ServiceC20S3.xml"/><service address="services/ServiceC52S2.xml"/><service address="services/ServiceC366S3.xml"/><service address="services/ServiceC49S4.xml"/><service address="services/ServiceC49S5.xml"/><service address="services/ServiceC52S7.xml"/><service address="services/ServiceC332S6.xml"/><service address="services/ServiceC332S11.xml"/><service address="services/ServiceC363S10.xml"/><service address="services/ServiceC332S1.xml"/><service address="services/ServiceC7S4.xml"/><service address="services/ServiceC19S1.xml"/><service address="services/ServiceC49S2.xml"/><service address="services/ServiceC108S4.xml"/><service address="services/ServiceC313S9.xml"/><service address="services/ServiceC318S8.xml"/><service address="services/ServiceC46S1.xml"/><service address="services/ServiceC313S4.xml"/><service address="services/ServiceC20S5.xml"/><service address="services/ServiceC108S5.xml"/><service address="services/ServiceC332S4.xml"/><service address="services/ServiceC50S1.xml"/><service address="services/ServiceC18S3.xml"/><service address="services/ServiceC46S2.xml"/><service address="services/ServiceC18S1.xml"/><service address="services/ServiceC52S6.xml"/><service address="services/ServiceC108S2.xml"/><service address="services/ServiceC49S1.xml"/><service address="services/ServiceC363S8.xml"/><service address="services/ServiceC318S12.xml"/><service address="services/ServiceC313S6.xml"/><service address="services/ServiceC313S7.xml"/><service address="services/ServiceC52S1.xml"/><service address="services/ServiceC313S5.xml"/><service address="services/ServiceC108S3.xml"/><service address="services/ServiceC7S2.xml"/><service address="services/ServiceC19S7.xml"/><service address="services/ServiceC366S4.xml"/><service address="services/ServiceC318S4.xml"/><service address="services/ServiceC318S9.xml"/><service address="services/ServiceC332S12.xml"/><service address="services/ServiceC52S4.xml"/><service address="services/ServiceC46S5.xml"/><service address="services/ServiceC51S5.xml"/><service address="services/ServiceC366S11.xml"/><service address="services/ServiceC5S1.xml"/><service address="services/ServiceC19S2.xml"/><service address="services/ServiceC7S3.xml"/><service address="services/ServiceC318S10.xml"/><service address="services/ServiceC1S1.xml"/><service address="services/ServiceC19S6.xml"/><service address="services/ServiceC332S10.xml"/><service address="services/ServiceC366S13.xml"/><service address="services/ServiceC51S4.xml"/><service address="services/ServiceC332S5.xml"/><service address="services/ServiceC5S3.xml"/><service address="services/ServiceC332S2.xml"/><service address="services/ServiceC318S2.xml"/><service address="services/ServiceC63S5.xml"/><service address="services/ServiceC363S4.xml"/><service address="services/ServiceC51S1.xml"/><service address="services/ServiceC366S1.xml"/><service address="services/ServiceC363S2.xml"/><service address="services/ServiceC63S4.xml"/><service address="services/ServiceC18S2.xml"/><service address="services/ServiceC63S3.xml"/><service address="services/ServiceC366S2.xml"/><service address="services/ServiceC363S12.xml"/><service address="services/ServiceC366S12.xml"/><service address="services/ServiceC49S7.xml"/><service address="services/ServiceC318S6.xml"/><service address="services/ServiceC332S8.xml"/><service address="services/ServiceC49S6.xml"/><service address="services/ServiceC52S3.xml"/><service address="services/ServiceC108S1.xml"/><service address="services/ServiceC52S5.xml"/><service address="services/ServiceC318S11.xml"/><service address="services/ServiceC318S5.xml"/><service address="services/ServiceC318S7.xml"/><service address="services/ServiceC50S3.xml"/><service address="services/ServiceC332S3.xml"/><service address="services/ServiceC366S9.xml"/><service address="services/ServiceC51S2.xml"/><service address="services/ServiceC313S3.xml"/><service address="services/ServiceC313S1.xml"/><service address="services/ServiceC108S6.xml"/><service address="services/ServiceC363S11.xml"/><service address="services/ServiceC50S2.xml"/><service address="services/ServiceC46S3.xml"/><service address="services/ServiceC20S4.xml"/><service address="services/ServiceC366S8.xml"/><service address="services/ServiceC7S1.xml"/><service address="services/ServiceC20S1.xml"/><service address="services/ServiceC50S4.xml"/><service address="services/ServiceC366S5.xml"/><service address="services/ServiceC1S2.xml"/><service address="services/ServiceC19S3.xml"/><service address="services/ServiceC49S8.xml"/><service address="services/ServiceC63S1.xml"/><service address="services/ServiceC332S7.xml"/><service address="services/ServiceC332S9.xml"/><service address="services/ServiceC18S4.xml"/><service address="services/ServiceC51S3.xml"/><service address="services/ServiceC20S2.xml"/><service address="services/ServiceC363S5.xml"/><service address="services/ServiceC363S9.xml"/><service address="services/ServiceC366S7.xml"/><service address="services/ServiceC366S6.xml"/><service address="services/ServiceC49S3.xml"/><service address="services/ServiceC46S4.xml"/><service address="services/ServiceC366S10.xml"/><service address="services/ServiceC5S2.xml"/><service address="services/ServiceC50S5.xml"/><service address="services/ServiceC318S1.xml"/><service address="services/ServiceC363S1.xml"/><service address="services/ServiceC63S2.xml"/><service address="services/ServiceC19S4.xml"/><service address="services/ServiceC313S2.xml"/><service address="services/ServiceC313S8.xml"/><service address="services/ServiceC19S5.xml"/><service address="services/ServiceC318S3.xml"/><service address="services/ServiceC363S3.xml"/><service address="services/ServiceC363S7.xml"/><service address="services/ServiceC318S5ServiceC7S3.xml"/><service address="services/ServiceC19S4ServiceC332S2.xml"/><service address="services/ServiceC332S4ServiceC46S1.xml"/><service address="services/ServiceC318S11ServiceC363S5.xml"/><service address="services/ServiceC5S2ServiceC366S6.xml"/><service address="services/ServiceC108S5ServiceC46S2.xml"/><service address="services/ServiceC52S2ServiceC366S12.xml"/><service address="services/ServiceC50S5ServiceC19S5.xml"/><service address="services/ServiceC63S2ServiceC18S3.xml"/><service address="services/ServiceC318S5ServiceC366S5.xml"/><service address="services/ServiceC19S5ServiceC313S5.xml"/><service address="services/ServiceC50S2ServiceC366S7.xml"/><service address="services/ServiceC49S6ServiceC63S5.xml"/><service address="services/ServiceC51S2ServiceC108S2.xml"/><service address="services/ServiceC50S1ServiceC313S2.xml"/><service address="services/ServiceC318S3ServiceC363S3.xml"/><service address="services/ServiceC363S12ServiceC366S5.xml"/><service address="services/ServiceC318S9ServiceC366S12.xml"/><service address="services/ServiceC52S1ServiceC63S3.xml"/><service address="services/ServiceC366S1ServiceC318S8.xml"/><service address="services/ServiceC108S4ServiceC19S1.xml"/><service address="services/ServiceC50S4ServiceC313S4.xml"/><service address="services/ServiceC363S11ServiceC366S5.xml"/><service address="services/ServiceC366S1ServiceC108S3.xml"/><service address="services/ServiceC318S2ServiceC50S3.xml"/><service address="services/ServiceC52S5ServiceC63S2.xml"/><service address="services/ServiceC20S1ServiceC366S1.xml"/><service address="services/ServiceC19S7ServiceC49S2.xml"/><service address="services/ServiceC1S2ServiceC332S8.xml"/><service address="services/ServiceC366S12ServiceC313S9.xml"/><service address="services/ServiceC51S1ServiceC363S1.xml"/><service address="services/ServiceC366S4ServiceC332S2.xml"/><service address="services/ServiceC49S1ServiceC20S1.xml"/><service address="services/ServiceC46S3ServiceC366S13.xml"/><service address="services/ServiceC19S7ServiceC50S4.xml"/><service address="services/ServiceC49S6ServiceC313S7.xml"/><service address="services/ServiceC366S12ServiceC52S7.xml"/><service address="services/ServiceC52S2ServiceC366S9.xml"/><service address="services/ServiceC313S5ServiceC366S3.xml"/><service address="services/ServiceC49S4ServiceC108S1.xml"/><service address="services/ServiceC366S4ServiceC5S2.xml"/><service address="services/ServiceC108S2ServiceC366S9.xml"/><service address="services/ServiceC108S4ServiceC7S3.xml"/><service address="services/ServiceC108S2ServiceC49S2.xml"/><service address="services/ServiceC332S11ServiceC52S3.xml"/><service address="services/ServiceC332S6ServiceC363S4.xml"/><service address="services/ServiceC363S10ServiceC19S1.xml"/><service address="services/ServiceC108S4ServiceC49S8.xml"/><service address="services/ServiceC332S4ServiceC1S1.xml"/><service address="services/ServiceC313S3ServiceC20S1.xml"/><service address="services/ServiceC50S5ServiceC366S6.xml"/><service address="services/ServiceC49S7ServiceC63S3.xml"/><service address="services/ServiceC7S3ServiceC51S5.xml"/><service address="services/ServiceC5S1ServiceC332S1.xml"/><service address="services/ServiceC363S9ServiceC318S2.xml"/><service address="services/ServiceC7S1ServiceC50S3.xml"/><service address="services/ServiceC49S3ServiceC318S9.xml"/><service address="services/ServiceC332S9ServiceC363S5.xml"/><service address="services/ServiceC18S2ServiceC332S4.xml"/><service address="services/ServiceC318S2ServiceC18S1.xml"/><service address="services/ServiceC51S1ServiceC49S6.xml"/><service address="services/ServiceC363S9ServiceC52S6.xml"/><service address="services/ServiceC49S1ServiceC318S8.xml"/><service address="services/ServiceC313S4ServiceC1S2.xml"/><service address="services/ServiceC52S6ServiceC51S4.xml"/><service address="services/ServiceC1S2ServiceC366S11.xml"/><service address="services/ServiceC52S2ServiceC332S7.xml"/><service address="services/ServiceC366S7ServiceC19S3.xml"/><service address="services/ServiceC108S4ServiceC366S3.xml"/><service address="services/ServiceC108S1ServiceC49S2.xml"/><service address="services/ServiceC363S1ServiceC318S7.xml"/><service address="services/ServiceC332S6ServiceC366S9.xml"/><service address="services/ServiceC363S12ServiceC332S9.xml"/><service address="services/ServiceC332S12ServiceC108S2.xml"/><service address="services/ServiceC313S2ServiceC366S11.xml"/><service address="services/ServiceC332S6ServiceC318S7.xml"/><service address="services/ServiceC366S10ServiceC366S11.xml"/><service address="services/ServiceC5S1ServiceC318S1.xml"/><service address="services/ServiceC363S7ServiceC52S6.xml"/><service address="services/ServiceC318S10ServiceC18S4.xml"/><service address="services/ServiceC5S3ServiceC7S3.xml"/><service address="services/ServiceC313S9ServiceC363S12.xml"/><service address="services/ServiceC49S5ServiceC51S5.xml"/><service address="services/ServiceC51S3ServiceC366S5.xml"/><service address="services/ServiceC108S4ServiceC7S4.xml"/><service address="services/ServiceC366S2ServiceC366S4.xml"/><service address="services/ServiceC49S6ServiceC63S1.xml"/><service address="services/ServiceC313S2ServiceC49S2.xml"/><service address="services/ServiceC363S7ServiceC318S6.xml"/><service address="services/ServiceC108S4ServiceC52S6.xml"/><service address="services/ServiceC366S8ServiceC366S10.xml"/><service address="services/ServiceC366S11ServiceC49S7.xml"/><service address="services/ServiceC366S7ServiceC313S6.xml"/><service address="services/ServiceC7S4ServiceC363S2.xml"/><service address="services/ServiceC363S11ServiceC313S1.xml"/><service address="services/ServiceC313S3ServiceC19S4.xml"/><service address="services/ServiceC363S12ServiceC46S4.xml"/><service address="services/ServiceC366S10ServiceC363S11.xml"/><service address="services/ServiceC363S12ServiceC18S2.xml"/><service address="services/ServiceC49S4ServiceC313S3.xml"/><service address="services/ServiceC332S6ServiceC366S11.xml"/><service address="services/ServiceC49S6ServiceC46S2.xml"/><service address="services/ServiceC7S4ServiceC52S4.xml"/><service address="services/ServiceC332S11ServiceC51S1.xml"/><service address="services/ServiceC363S10ServiceC363S1.xml"/><service address="services/ServiceC49S2ServiceC332S10.xml"/><service address="services/ServiceC318S8ServiceC52S4.xml"/><service address="services/ServiceC318S5ServiceC313S3.xml"/><service address="services/ServiceC313S6ServiceC366S10.xml"/><service address="services/ServiceC366S12ServiceC363S4.xml"/><service address="services/ServiceC18S4ServiceC19S5.xml"/><service address="services/ServiceC332S7ServiceC318S8.xml"/><service address="services/ServiceC50S5ServiceC20S1.xml"/><service address="services/ServiceC18S2ServiceC19S6.xml"/><service address="services/ServiceC363S3ServiceC363S1.xml"/><service address="services/ServiceC363S5ServiceC18S2.xml"/><service address="services/ServiceC363S12ServiceC49S8.xml"/><service address="services/ServiceC19S7ServiceC332S11.xml"/><service address="services/ServiceC50S2ServiceC363S4.xml"/><service address="services/ServiceC318S6ServiceC5S1.xml"/><service address="services/ServiceC20S1ServiceC108S4.xml"/><service address="services/ServiceC313S3ServiceC332S7.xml"/><service address="services/ServiceC318S5ServiceC363S6.xml"/><service address="services/ServiceC363S12ServiceC313S5.xml"/><service address="services/ServiceC18S1ServiceC313S9.xml"/><service address="services/ServiceC7S3ServiceC363S10.xml"/></services></configuration>