<?xml version="1.0" encoding="UTF-8" standalone="no"?><rdf:RDF xmlns:rdf="http://www.w3.org/1999/02/22-rdf-syntax-ns#" xmlns:daml="http://www.daml.org/2001/03/daml+oil" xmlns:expr="http://www.daml.org/services/owl-s/1.2/generic/Expression.owl#" xmlns:owl="http://www.w3.org/2002/07/owl#" xmlns:process="http://www.daml.org/services/owl-s/1.2/Process.owl#" xmlns:rdfs="http://www.w3.org/2000/01/rdf-schema#" xmlns:service="http://www.daml.org/services/owl-s/1.2/Service.owl#" xmlns:swrl="http://www.w3.org/2003/11/swrl#" xml:base="http://magus.online/evaluation/service/service/ServiceC236S4ServiceC99S5"><service:Service rdf:ID="ServiceC236S4ServiceC99S5"><service:describedBy><process:AtomicProcess rdf:ID="ServiceC236S4ServiceC99S5Process"><service:describes rdf:resource="#ServiceC236S4ServiceC99S5"/><process:hasInput><process:Input rdf:ID="inpc52df7e2d1"><process:parameterType rdf:datatype="http://www.w3.org/2001/XMLSchema#anyURI">http://ls3.rnet.ryerson.ca/people/mahdi/magus/owl/eval.owl#c52df7e2d</process:parameterType></process:Input></process:hasInput><process:hasInput><process:Input rdf:ID="inpc0fc867ab1"><process:parameterType rdf:datatype="http://www.w3.org/2001/XMLSchema#anyURI">http://ls3.rnet.ryerson.ca/people/mahdi/magus/owl/eval.owl#c0fc867ab</process:parameterType></process:Input></process:hasInput><process:hasInput><process:Input rdf:ID="inpcaecc9d6f1"><process:parameterType rdf:datatype="http://www.w3.org/2001/XMLSchema#anyURI">http://ls3.rnet.ryerson.ca/people/mahdi/magus/owl/eval.owl#caecc9d6f</process:parameterType></process:Input></process:hasInput><process:hasInput><process:Input rdf:ID="inpc7326ab6c1"><process:parameterType rdf:datatype="http://www.w3.org/2001/XMLSchema#anyURI">http://ls3.rnet.ryerson.ca/people/mahdi/magus/owl/eval.owl#c7326ab6c</process:parameterType></process:Input></process:hasInput><process:hasOutput><process:Output rdf:ID="outc7b3db5d71"><process:parameterType rdf:datatype="http://www.w3.org/2001/XMLSchema#anyURI">http://ls3.rnet.ryerson.ca/people/mahdi/magus/owl/eval.owl#c7b3db5d7</process:parameterType></process:Output></process:hasOutput><process:hasOutput><process:Output rdf:ID="outc0a670e541"><process:parameterType rdf:datatype="http://www.w3.org/2001/XMLSchema#anyURI">http://ls3.rnet.ryerson.ca/people/mahdi/magus/owl/eval.owl#c0a670e54</process:parameterType></process:Output></process:hasOutput><process:hasOutput><process:Output rdf:ID="outc04d7f5631"><process:parameterType rdf:datatype="http://www.w3.org/2001/XMLSchema#anyURI">http://ls3.rnet.ryerson.ca/people/mahdi/magus/owl/eval.owl#c04d7f563</process:parameterType></process:Output></process:hasOutput><process:hasOutput><process:Output rdf:ID="outc7b825b021"><process:parameterType rdf:datatype="http://www.w3.org/2001/XMLSchema#anyURI">http://ls3.rnet.ryerson.ca/people/mahdi/magus/owl/eval.owl#c7b825b02</process:parameterType></process:Output></process:hasOutput><process:hasOutput><process:Output rdf:ID="outc3b9372901"><process:parameterType rdf:datatype="http://www.w3.org/2001/XMLSchema#anyURI">http://ls3.rnet.ryerson.ca/people/mahdi/magus/owl/eval.owl#c3b937290</process:parameterType></process:Output></process:hasOutput><process:hasOutput><process:Output rdf:ID="outcfd79af2a1"><process:parameterType rdf:datatype="http://www.w3.org/2001/XMLSchema#anyURI">http://ls3.rnet.ryerson.ca/people/mahdi/magus/owl/eval.owl#cfd79af2a</process:parameterType></process:Output></process:hasOutput><process:hasPrecondition><expr:SWRL-Condition rdf:ID="ServiceC236S4ServiceC99S5Prec"><expr:expressionObject><swrl:AtomList><rdf:first><swrl:ClassAtom><swrl:classPredicate rdf:resource="http://ls3.rnet.ryerson.ca/people/mahdi/magus/owl/eval.owl#c52df7e2d"/><swrl:argument1 rdf:resource="http://magus.online/evaluation/service/service/ServiceC236S4ServiceC99S5#inpc52df7e2d1"/></swrl:ClassAtom></rdf:first><rdf:rest><swrl:AtomList><rdf:first><swrl:ClassAtom><swrl:classPredicate rdf:resource="http://ls3.rnet.ryerson.ca/people/mahdi/magus/owl/eval.owl#c0fc867ab"/><swrl:argument1 rdf:resource="http://magus.online/evaluation/service/service/ServiceC236S4ServiceC99S5#inpc0fc867ab1"/></swrl:ClassAtom></rdf:first><rdf:rest><swrl:AtomList><rdf:first><swrl:ClassAtom><swrl:classPredicate rdf:resource="http://ls3.rnet.ryerson.ca/people/mahdi/magus/owl/eval.owl#caecc9d6f"/><swrl:argument1 rdf:resource="http://magus.online/evaluation/service/service/ServiceC236S4ServiceC99S5#inpcaecc9d6f1"/></swrl:ClassAtom></rdf:first><rdf:rest><swrl:AtomList><rdf:first><swrl:ClassAtom><swrl:classPredicate rdf:resource="http://ls3.rnet.ryerson.ca/people/mahdi/magus/owl/eval.owl#c7326ab6c"/><swrl:argument1 rdf:resource="http://magus.online/evaluation/service/service/ServiceC236S4ServiceC99S5#inpc7326ab6c1"/></swrl:ClassAtom></rdf:first><rdf:rest rdf:resource="http://www.w3.org/1999/02/22-rdf-syntax-ns#nil"/></swrl:AtomList></rdf:rest></swrl:AtomList></rdf:rest></swrl:AtomList></rdf:rest></swrl:AtomList></expr:expressionObject><expr:expressionLanguage rdf:resource="http://www.daml.org/services/owl-s/1.2/generic/Expression.owl#SWRL"/></expr:SWRL-Condition></process:hasPrecondition><process:hasResult><expr:SWRL-Condition rdf:ID="ServiceC236S4ServiceC99S5Eff"><expr:expressionObject><swrl:AtomList><rdf:first><swrl:IndividualPropertyAtom><swrl:propertyPredicate rdf:resource="http://ls3.rnet.ryerson.ca/people/mahdi/magus/owl/eval.owl#p0ff27b4f"/><swrl:argument1 rdf:resource="http://magus.online/evaluation/service/service/ServiceC236S4ServiceC99S5#outc3b9372901"/><swrl:argument2 rdf:resource="http://magus.online/evaluation/service/service/ServiceC236S4ServiceC99S5#outc7b3db5d71"/></swrl:IndividualPropertyAtom></rdf:first><rdf:rest><swrl:AtomList><rdf:first><swrl:IndividualPropertyAtom><swrl:propertyPredicate rdf:resource="http://ls3.rnet.ryerson.ca/people/mahdi/magus/owl/eval.owl#p2afad74f"/><swrl:argument1 rdf:resource="http://magus.online/evaluation/service/service/ServiceC236S4ServiceC99S5#outc0a670e541"/><swrl:argument2 rdf:resource="http://magus.online/evaluation/service/service/ServiceC236S4ServiceC99S5#outc04d7f5631"/></swrl:IndividualPropertyAtom></rdf:first><rdf:rest><swrl:AtomList><rdf:first><swrl:IndividualPropertyAtom><swrl:propertyPredicate rdf:resource="http://ls3.rnet.ryerson.ca/people/mahdi/magus/owl/eval.owl#p3ff62c1e"/><swrl:argument1 rdf:resource="http://magus.online/evaluation/service/service/ServiceC236S4ServiceC99S5#outcfd79af2a1"/><swrl:argument2 rdf:resource="http://magus.online/evaluation/service/service/ServiceC236S4ServiceC99S5#inpc0fc867ab1"/></swrl:IndividualPropertyAtom></rdf:first><rdf:rest rdf:resource="http://www.w3.org/1999/02/22-rdf-syntax-ns#nil"/></swrl:AtomList></rdf:rest></swrl:AtomList></rdf:rest></swrl:AtomList></expr:expressionObject><expr:expressionLanguage rdf:resource="http://www.daml.org/services/owl-s/1.2/generic/Expression.owl#SWRL"/></expr:SWRL-Condition></process:hasResult></process:AtomicProcess></service:describedBy></service:Service></rdf:RDF>