<?xml version="1.0" encoding="UTF-16"?><rdf:RDF xml:base="http://magus.online/evaluation/service/service/ServiceC25S3" xmlns:daml="http://www.daml.org/2001/03/daml+oil" xmlns:expr="http://www.daml.org/services/owl-s/1.2/generic/Expression.owl#" xmlns:owl="http://www.w3.org/2002/07/owl#" xmlns:process="http://www.daml.org/services/owl-s/1.2/Process.owl#" xmlns:rdf="http://www.w3.org/1999/02/22-rdf-syntax-ns#" xmlns:rdfs="http://www.w3.org/2000/01/rdf-schema#" xmlns:service="http://www.daml.org/services/owl-s/1.2/Service.owl#" xmlns:swrl="http://www.w3.org/2003/11/swrl#"><service:Service rdf:ID="ServiceC25S3"><service:describedBy><process:AtomicProcess rdf:ID="ServiceC25S3Process"><service:describes rdf:resource="#ServiceC25S3"/><process:hasInput><process:Input rdf:ID="inpc2eae0c031"><process:parameterType rdf:datatype="http://www.w3.org/2001/XMLSchema#anyURI">http://ls3.rnet.ryerson.ca/people/mahdi/magus/owl/eval.owl#c2eae0c03</process:parameterType></process:Input></process:hasInput><process:hasInput><process:Input rdf:ID="inpc04d7f5631"><process:parameterType rdf:datatype="http://www.w3.org/2001/XMLSchema#anyURI">http://ls3.rnet.ryerson.ca/people/mahdi/magus/owl/eval.owl#c04d7f563</process:parameterType></process:Input></process:hasInput><process:hasOutput><process:Output rdf:ID="outc6085cf851"><process:parameterType rdf:datatype="http://www.w3.org/2001/XMLSchema#anyURI">http://ls3.rnet.ryerson.ca/people/mahdi/magus/owl/eval.owl#c6085cf85</process:parameterType></process:Output></process:hasOutput><process:hasOutput><process:Output rdf:ID="outcaecc9d6f1"><process:parameterType rdf:datatype="http://www.w3.org/2001/XMLSchema#anyURI">http://ls3.rnet.ryerson.ca/people/mahdi/magus/owl/eval.owl#caecc9d6f</process:parameterType></process:Output></process:hasOutput><process:hasPrecondition><expr:SWRL-Condition rdf:ID="ServiceC25S3Prec"><expr:expressionObject><swrl:AtomList><rdf:first><swrl:ClassAtom><swrl:classPredicate rdf:resource="http://ls3.rnet.ryerson.ca/people/mahdi/magus/owl/eval.owl#c2eae0c03"/><swrl:argument1 rdf:resource="http://magus.online/evaluation/service/service/ServiceC25S3#inpc2eae0c031"/></swrl:ClassAtom></rdf:first><rdf:rest><swrl:AtomList><rdf:first><swrl:ClassAtom><swrl:classPredicate rdf:resource="http://ls3.rnet.ryerson.ca/people/mahdi/magus/owl/eval.owl#c04d7f563"/><swrl:argument1 rdf:resource="http://magus.online/evaluation/service/service/ServiceC25S3#inpc04d7f5631"/></swrl:ClassAtom></rdf:first><rdf:rest><swrl:AtomList><rdf:first><swrl:IndividualPropertyAtom><swrl:propertyPredicate rdf:resource="http://ls3.rnet.ryerson.ca/people/mahdi/magus/owl/eval.owl#pb8e07902"/><swrl:argument1 rdf:resource="http://magus.online/evaluation/service/service/ServiceC25S3#inpc2eae0c031"/><swrl:argument2 rdf:resource="http://magus.online/evaluation/service/service/ServiceC25S3#inpc04d7f5631"/></swrl:IndividualPropertyAtom></rdf:first><rdf:rest rdf:resource="http://www.w3.org/1999/02/22-rdf-syntax-ns#nil"/></swrl:AtomList></rdf:rest></swrl:AtomList></rdf:rest></swrl:AtomList></expr:expressionObject><expr:expressionLanguage rdf:resource="http://www.daml.org/services/owl-s/1.2/generic/Expression.owl#SWRL"/></expr:SWRL-Condition></process:hasPrecondition><process:hasResult><expr:SWRL-Condition rdf:ID="ServiceC25S3Eff"><expr:expressionObject><swrl:AtomList><rdf:first><swrl:IndividualPropertyAtom><swrl:propertyPredicate rdf:resource="http://ls3.rnet.ryerson.ca/people/mahdi/magus/owl/eval.owl#p74792c42"/><swrl:argument1 rdf:resource="http://magus.online/evaluation/service/service/ServiceC25S3#outc6085cf851"/><swrl:argument2 rdf:resource="http://magus.online/evaluation/service/service/ServiceC25S3#outcaecc9d6f1"/></swrl:IndividualPropertyAtom></rdf:first><rdf:rest><swrl:AtomList><rdf:first><swrl:IndividualPropertyAtom><swrl:propertyPredicate rdf:resource="http://ls3.rnet.ryerson.ca/people/mahdi/magus/owl/eval.owl#pe273c43a"/><swrl:argument1 rdf:resource="http://magus.online/evaluation/service/service/ServiceC25S3#inpc04d7f5631"/><swrl:argument2 rdf:resource="http://magus.online/evaluation/service/service/ServiceC25S3#outcaecc9d6f1"/></swrl:IndividualPropertyAtom></rdf:first><rdf:rest rdf:resource="http://www.w3.org/1999/02/22-rdf-syntax-ns#nil"/></swrl:AtomList></rdf:rest></swrl:AtomList></expr:expressionObject><expr:expressionLanguage rdf:resource="http://www.daml.org/services/owl-s/1.2/generic/Expression.owl#SWRL"/></expr:SWRL-Condition></process:hasResult></process:AtomicProcess></service:describedBy></service:Service></rdf:RDF>